himspace.py
himspace-0.1.dist-info/entry_points.txt
himspace-0.1.dist-info/WHEEL
himspace-0.1.dist-info/METADATA
himspace-0.1.dist-info/RECORD
