Metadata-Version: 2.1
Name: himspace
Version: 0.1
Summary: 获取文件|文件夹容量
Keywords: 
Author-email: jutooy <jutooy@qq.com>
Classifier: License :: OSI Approved :: Apache Software License
